MANIFEST.in
README.md
requirements.txt
setup.py
dmcode/__init__.py
dmcode/__main__.py
dmcode/dmcode.py
dmcode/dmcode_init.py
dmcode/settings.py
dmcode.egg-info/PKG-INFO
dmcode.egg-info/SOURCES.txt
dmcode.egg-info/dependency_links.txt
dmcode.egg-info/entry_points.txt
dmcode.egg-info/requires.txt
dmcode.egg-info/top_level.txt
dmcode/util/error.py
dmcode/util/file.py
dmcode/util/ftp.py
dmcode/util/paste.py
dmcode/util/sftp.py