Metadata-Version: 2.1
Name: dmcode
Version: 0.9b0
Summary: Allows you to upload your code to an ftp server without any ftp-clients.
Home-page: https://github.com/foozzi/dmcode
Author: Tkachenko Igor
Author-email: foozzione@gmail.com
License: GNU
Download-URL: https://github.com/foozzi/dmcode/archive/0.9b0.tar.gz
Keywords: ftp,ftp-client,deploy,upload
Platform: UNKNOWN
Classifier: Development Status :: 4 - Beta
Classifier: Environment :: Console
Classifier: Operating System :: POSIX :: Linux
Classifier: Operating System :: MacOS
Classifier: License :: OSI Approved :: GNU General Public License v3 (GPLv3)
Classifier: Programming Language :: Python :: 3 :: Only
